tttracking/__init__.py
tttracking-0.0.1.1.dist-info/METADATA
tttracking-0.0.1.1.dist-info/WHEEL
tttracking-0.0.1.1.dist-info/top_level.txt
tttracking-0.0.1.1.dist-info/RECORD
