Metadata-Version: 2.1
Name: tttracking
Version: 0.0.1.1
Summary: TTtracking MVP
Author: Pedro Bacelar
License: MIT
